CAM2CameraDatabaseAPIClient/__init__.py
CAM2CameraDatabaseAPIClient/camera.py
CAM2CameraDatabaseAPIClient/client.py
CAM2CameraDatabaseAPIClient/config.py
CAM2CameraDatabaseAPIClient/error.py
CAM2CameraDatabaseAPIClient/tests/__init__.py
CAM2CameraDatabaseAPIClient/tests/test_camera.py
CAM2CameraDatabaseAPIClient/tests/test_client.py
CAM2CameraDatabaseClient-1.0.2.dist-info/METADATA
CAM2CameraDatabaseClient-1.0.2.dist-info/RECORD
CAM2CameraDatabaseClient-1.0.2.dist-info/WHEEL
CAM2CameraDatabaseClient-1.0.2.dist-info/top_level.txt
