Metadata-Version: 2.1
Name: CAM2CameraDatabaseClient
Version: 1.0.2
Summary: A python wrapper of CAM2 database API
Home-page: https://github.com/PurdueCAM2Project/CameraDatabaseClient
Author: Purdue CAM2 Research Group
Author-email: cam2proj@ecn.purdue.edu
License: UNKNOWN
Keywords: API,camera,database,CAM2
Platform: UNKNOWN
Classifier: Development Status :: 3 - Alpha
Classifier: Programming Language :: Python :: 2.7
Classifier: Programming Language :: Python :: 3.6
Requires-Python: >=2.7
Requires-Dist: requests
